opentelemetry/proto/__init__.py
opentelemetry/proto/version.py
opentelemetry/proto/collector/__init__.py
opentelemetry/proto/collector/logs/v1/logs_service_pb2.py
opentelemetry/proto/collector/logs/v1/logs_service_pb2.pyi
opentelemetry/proto/collector/logs/v1/logs_service_pb2_grpc.py
opentelemetry/proto/collector/metrics/__init__.py
opentelemetry/proto/collector/metrics/v1/__init__.py
opentelemetry/proto/collector/metrics/v1/metrics_service_pb2.py
opentelemetry/proto/collector/metrics/v1/metrics_service_pb2.pyi
opentelemetry/proto/collector/metrics/v1/metrics_service_pb2_grpc.py
opentelemetry/proto/collector/trace/__init__.py
opentelemetry/proto/collector/trace/v1/__init__.py
opentelemetry/proto/collector/trace/v1/trace_service_pb2.py
opentelemetry/proto/collector/trace/v1/trace_service_pb2.pyi
opentelemetry/proto/collector/trace/v1/trace_service_pb2_grpc.py
opentelemetry/proto/common/__init__.py
opentelemetry/proto/common/v1/__init__.py
opentelemetry/proto/common/v1/common_pb2.py
opentelemetry/proto/common/v1/common_pb2.pyi
opentelemetry/proto/logs/v1/logs_pb2.py
opentelemetry/proto/logs/v1/logs_pb2.pyi
opentelemetry/proto/metrics/__init__.py
opentelemetry/proto/metrics/experimental/metrics_config_service_pb2.py
opentelemetry/proto/metrics/experimental/metrics_config_service_pb2.pyi
opentelemetry/proto/metrics/experimental/metrics_config_service_pb2_grpc.py
opentelemetry/proto/metrics/v1/__init__.py
opentelemetry/proto/metrics/v1/metrics_pb2.py
opentelemetry/proto/metrics/v1/metrics_pb2.pyi
opentelemetry/proto/resource/__init__.py
opentelemetry/proto/resource/v1/__init__.py
opentelemetry/proto/resource/v1/resource_pb2.py
opentelemetry/proto/resource/v1/resource_pb2.pyi
opentelemetry/proto/trace/__init__.py
opentelemetry/proto/trace/v1/__init__.py
opentelemetry/proto/trace/v1/trace_config_pb2.py
opentelemetry/proto/trace/v1/trace_config_pb2.pyi
opentelemetry/proto/trace/v1/trace_pb2.py
opentelemetry/proto/trace/v1/trace_pb2.pyi
opentelemetry_proto-1.12.0.dist-info/LICENSE
opentelemetry_proto-1.12.0.dist-info/METADATA
opentelemetry_proto-1.12.0.dist-info/WHEEL
opentelemetry_proto-1.12.0.dist-info/top_level.txt
opentelemetry_proto-1.12.0.dist-info/RECORD
